fireapi/__init__.py
fireapi/api.py
fireapi/base.py
fireapi/exceptions.py
fireapi/version.py
fireapi-0.4.3.dist-info/LICENSE
fireapi-0.4.3.dist-info/METADATA
fireapi-0.4.3.dist-info/WHEEL
fireapi-0.4.3.dist-info/top_level.txt
fireapi-0.4.3.dist-info/RECORD
