Metadata-Version: 2.1
Name: fireapi
Version: 0.4.3
Summary: A simple API wrapper for the 24Fire REST API
Home-page: https://github.com/EvickaStudio/24-Fire-REST-API
Author: EvickaStudio
Author-email: hello@evicka.de
License: AGPL-3.0
Keywords: API,24Fire,KVM,Server Management
Classifier: Programming Language :: Python :: 3
Classifier: License :: OSI Approved :: GNU Affero General Public License v3
Classifier: Operating System :: OS Independent
License-File: LICENSE
Requires-Dist: aiohttp
Requires-Dist: requests
